city2graph/__init__.py
city2graph/base.py
city2graph/data.py
city2graph/graph.py
city2graph/metapath.py
city2graph/mobility.py
city2graph/morphology.py
city2graph/proximity.py
city2graph/transportation.py
city2graph/utils.py
city2graph-0.2.3.dist-info/METADATA
city2graph-0.2.3.dist-info/WHEEL
city2graph-0.2.3.dist-info/licenses/LICENSE
city2graph-0.2.3.dist-info/RECORD
