Metadata-Version: 2.4
Name: city2graph
Version: 0.2.3
Summary: A Python library for Geospatial Graph Neural Networks and GeoAI for Urban Analytics with PyTorch Geometric. Convert geospatial data to graphs for spatiotemporal analysis, urban mobility studies, and more.
Project-URL: Homepage, https://github.com/c2g-dev/city2graph
Project-URL: Documentation, https://city2graph.net
Project-URL: Bug Tracker, https://github.com/c2g-dev/city2graph/issues
Author-email: Yuta Sato <y.sato@liverpool.ac.uk>
License: BSD-3-Clause
License-File: LICENSE
Keywords: Digital Twin,GNNs,GeoAI,Geographic Data Science,Geospatial Analysis,Geospatial Foundation Models,Graph Neural Networks,Graph Representation Learning,PyTorch Geometric,Spatial Data Science,Spatial Knowledge Graphs,Spatiotemporal Analysis,Transportation Networks,Urban Analytics,Urban Informatics,Urban Mobility,Urban Planning and Design
Classifier: Development Status :: 4 - Beta
Classifier: Intended Audience :: Science/Research
Classifier: License :: OSI Approved :: BSD License
Classifier: Programming Language :: Python
Classifier: Programming Language :: Python :: 3 :: Only
Classifier: Programming Language :: Python :: 3.11
Classifier: Programming Language :: Python :: 3.12
Classifier: Programming Language :: Python :: 3.13
Classifier: Topic :: Scientific/Engineering :: GIS
Requires-Python: <3.14,>=3.11
Requires-Dist: geopandas>=1.1.1
Requires-Dist: libpysal>=4.12.1
Requires-Dist: momepy
Requires-Dist: networkx>=2.8
Requires-Dist: osmnx>=2.0.3
Requires-Dist: overturemaps>=0.17.0
Requires-Dist: rustworkx>=0.17.1
Requires-Dist: scipy>=1.10.0
Requires-Dist: shapely>=2.1.0
Provides-Extra: cpu
Requires-Dist: torch-geometric>=2.6.1; extra == 'cpu'
Requires-Dist: torch>=2.9.0; extra == 'cpu'
Requires-Dist: torchvision>=0.24.0; extra == 'cpu'
Provides-Extra: cu118
Requires-Dist: torch-geometric>=2.6.1; extra == 'cu118'
Requires-Dist: torch>=2.6.0; extra == 'cu118'
Requires-Dist: torchvision>=0.21.0; extra == 'cu118'
Provides-Extra: cu124
Requires-Dist: torch-geometric>=2.6.1; extra == 'cu124'
Requires-Dist: torch>=2.6.0; extra == 'cu124'
Requires-Dist: torchvision>=0.21.0; extra == 'cu124'
Provides-Extra: cu126
Requires-Dist: torch-geometric>=2.6.1; extra == 'cu126'
Requires-Dist: torch>=2.7.0; extra == 'cu126'
Requires-Dist: torchvision>=0.22.0; extra == 'cu126'
Provides-Extra: cu128
Requires-Dist: torch-geometric>=2.6.1; extra == 'cu128'
Requires-Dist: torch>=2.9.0; extra == 'cu128'
Requires-Dist: torchvision>=0.24.0; extra == 'cu128'
Provides-Extra: cu130
Requires-Dist: torch-geometric>=2.6.1; extra == 'cu130'
Requires-Dist: torch>=2.9.0; extra == 'cu130'
Requires-Dist: torchvision>=0.24.0; extra == 'cu130'
